perfstat/__init__.py
perfstat/__main__.py
perfstat/perfstat.py
perfstat-0.0.2.dist-info/METADATA
perfstat-0.0.2.dist-info/WHEEL
perfstat-0.0.2.dist-info/top_level.txt
perfstat-0.0.2.dist-info/RECORD
