Metadata-Version: 2.1
Name: perfstat
Version: 0.0.2
Summary: Capturing performance statistics
Home-page: UNKNOWN
Author: Ginko Balboa
Author-email: ginkobalboa3@gmail.com
License: UNKNOWN
Project-URL: github, https://github.com/GinkoBalboa/perfstat
Platform: UNKNOWN
Classifier: Development Status :: 4 - Beta
Classifier: Intended Audience :: Developers
Classifier: Programming Language :: Python :: 3.7
Classifier: Programming Language :: Python :: 3.8
Classifier: Programming Language :: Python :: 3.9
Classifier: Programming Language :: Python :: 3.10
Classifier: License :: OSI Approved :: GNU General Public License v3 (GPLv3)
Classifier: Operating System :: POSIX :: Linux
Classifier: Topic :: Software Development
Requires-Python: >=3.7
Requires-Dist: pandas
